pybind11_weaver/__init__.py
pybind11_weaver/config.py
pybind11_weaver/entity_tree.py
pybind11_weaver/gen_code.py
pybind11_weaver/gen_unit.py
pybind11_weaver/main.py
pybind11_weaver/entity/__init__.py
pybind11_weaver/entity/entity_base.py
pybind11_weaver/entity/enum.py
pybind11_weaver/entity/funktion.py
pybind11_weaver/entity/namespace.py
pybind11_weaver/entity/klass/__init__.py
pybind11_weaver/entity/klass/field.py
pybind11_weaver/entity/klass/klass.py
pybind11_weaver/entity/klass/method.py
pybind11_weaver/entity/klass/trampoline.py
pybind11_weaver/include/pybind11_weaver/pybind11_weaver.h
pybind11_weaver/third_party/ccsyspath.py
pybind11_weaver/utils/common.py
pybind11_weaver/utils/fn.py
pybind11_weaver/utils/scope_list.py
pybind11_weaver-0.1.3.dist-info/LICENSE
pybind11_weaver-0.1.3.dist-info/METADATA
pybind11_weaver-0.1.3.dist-info/WHEEL
pybind11_weaver-0.1.3.dist-info/entry_points.txt
pybind11_weaver-0.1.3.dist-info/top_level.txt
pybind11_weaver-0.1.3.dist-info/RECORD
