Metadata-Version: 2.1
Name: pybind11_weaver
Version: 0.1.3
Summary: A fully customizable pybind11 generator to help generate code for exsiting c/c++ library.
License: MIT
Project-URL: Homepage, https://github.com/edimetia3d/pybind11_weaver
Project-URL: Documentation, https://github.com/edimetia3d/pybind11_weaver
Project-URL: Repository, https://github.com/edimetia3d/pybind11_weaver
Project-URL: Changelog, https://github.com/edimetia3d/pybind11_weaver/releases
Keywords: pybind11,generator,codegen,gen
Classifier: Development Status :: 1 - Planning
Classifier: Environment :: Console
Classifier: Intended Audience :: Developers
Classifier: License :: OSI Approved :: MIT License
Classifier: Programming Language :: Python :: 3
Classifier: Programming Language :: C++
Classifier: Topic :: Software Development :: Code Generators
Classifier: Topic :: Software Development :: Compilers
License-File: LICENSE
Requires-Dist: pylibclang
Requires-Dist: PyYAML
Requires-Dist: pybind11
Requires-Dist: attrs
